{"lastUsed":1664416937282,"path":"\/Users\/eddie\/Desktop\/CS 5004\/workplace","projectCount":5,"recentFiles":[{"path":"\/Lab02\/test","parentWorkspace":"\/Users\/eddie\/Desktop\/CS 5004\/workplace","name":"EmployeeTest.java","lastModified":1664328817031,"locationURI":"file:\/Users\/eddie\/Desktop\/CS%205004\/workplace\/Lab02\/test\/EmployeeTest.java"},{"path":"\/homework01\/src","parentWorkspace":"\/Users\/eddie\/Desktop\/CS 5004\/workplace","name":"Vector3D.java","lastModified":1663727063834,"locationURI":"file:\/Users\/eddie\/Desktop\/CS%205004\/workplace\/homework01\/src\/Vector3D.java"},{"path":"\/Lab02\/test","parentWorkspace":"\/Users\/eddie\/Desktop\/CS 5004\/workplace","name":"FibonacciCounterTest.java","lastModified":1664328127742,"locationURI":"file:\/Users\/eddie\/Desktop\/CS%205004\/workplace\/Lab02\/test\/FibonacciCounterTest.java"},{"path":"\/lab01\/src\/lab01","parentWorkspace":"\/Users\/eddie\/Desktop\/CS 5004\/workplace","name":"Contact.java","lastModified":1663204828450,"locationURI":"file:\/Users\/eddie\/Desktop\/CS%205004\/workplace\/lab01\/src\/lab01\/Contact.java"},{"path":"\/lab01\/src\/lab01","parentWorkspace":"\/Users\/eddie\/Desktop\/CS 5004\/workplace","name":"Person.java","lastModified":1663249500990,"locationURI":"file:\/Users\/eddie\/Desktop\/CS%205004\/workplace\/lab01\/src\/lab01\/Person.java"},{"path":"\/lab01\/test\/lab01","parentWorkspace":"\/Users\/eddie\/Desktop\/CS 5004\/workplace","name":"ContactTest.java","lastModified":1663249263651,"locationURI":"file:\/Users\/eddie\/Desktop\/CS%205004\/workplace\/lab01\/test\/lab01\/ContactTest.java"},{"path":"\/Lab02\/test","parentWorkspace":"\/Users\/eddie\/Desktop\/CS 5004\/workplace","name":"PayCheckTest.java","lastModified":1664329362367,"locationURI":"file:\/Users\/eddie\/Desktop\/CS%205004\/workplace\/Lab02\/test\/PayCheckTest.java"},{"path":"\/lab00-Example\/src\/cs5004\/lab00","parentWorkspace":"\/Users\/eddie\/Desktop\/CS 5004\/workplace","name":"Person.java","lastModified":1663090544156},{"path":"\/lab00-Example\/test","parentWorkspace":"\/Users\/eddie\/Desktop\/CS 5004\/workplace","name":"PersonTest.java","lastModified":1662829925836},{"path":"\/homework01\/test","parentWorkspace":"\/Users\/eddie\/Desktop\/CS 5004\/workplace","name":"Vector3DTest.java","lastModified":1663872193040,"locationURI":"file:\/Users\/eddie\/Desktop\/CS%205004\/workplace\/homework01\/test\/Vector3DTest.java"},{"path":"\/Lab03\/src","parentWorkspace":"\/Users\/eddie\/Desktop\/CS 5004\/workplace","name":"AbstractTemperature.java","lastModified":1664416512126,"locationURI":"file:\/Users\/eddie\/Desktop\/CS%205004\/workplace\/Lab03\/src\/AbstractTemperature.java"},{"path":"\/lab00-Example\/test","parentWorkspace":"\/Users\/eddie\/Desktop\/CS 5004\/workplace","name":"BookTest.java","lastModified":1662829817768},{"path":"\/Lab02\/src","parentWorkspace":"\/Users\/eddie\/Desktop\/CS 5004\/workplace","name":"Employee.java","lastModified":1664329362367,"locationURI":"file:\/Users\/eddie\/Desktop\/CS%205004\/workplace\/Lab02\/src\/Employee.java"},{"path":"\/lab00-Example\/src\/cs5004\/lab00","parentWorkspace":"\/Users\/eddie\/Desktop\/CS 5004\/workplace","name":"Book.java","lastModified":1663078368787},{"path":"\/Lab03\/src","parentWorkspace":"\/Users\/eddie\/Desktop\/CS 5004\/workplace","name":"CelsiusTemperature.java","lastModified":1664416950835,"locationURI":"file:\/Users\/eddie\/Desktop\/CS%205004\/workplace\/Lab03\/src\/CelsiusTemperature.java"},{"path":"\/Lab03\/test","parentWorkspace":"\/Users\/eddie\/Desktop\/CS 5004\/workplace","name":"TemperatureTest.java","lastModified":1664416516560,"locationURI":"file:\/Users\/eddie\/Desktop\/CS%205004\/workplace\/Lab03\/test\/TemperatureTest.java"},{"path":"\/Lab03\/src","parentWorkspace":"\/Users\/eddie\/Desktop\/CS 5004\/workplace","name":"Temperature.java","lastModified":1664416518666,"locationURI":"file:\/Users\/eddie\/Desktop\/CS%205004\/workplace\/Lab03\/src\/Temperature.java"},{"path":"\/Lab03\/src","parentWorkspace":"\/Users\/eddie\/Desktop\/CS 5004\/workplace","name":"FahrenheitTemperature.java","lastModified":1664416937284,"locationURI":"file:\/Users\/eddie\/Desktop\/CS%205004\/workplace\/Lab03\/src\/FahrenheitTemperature.java"},{"path":"\/Lab02\/src","parentWorkspace":"\/Users\/eddie\/Desktop\/CS 5004\/workplace","name":"PayCheck.java","lastModified":1664329398661,"locationURI":"file:\/Users\/eddie\/Desktop\/CS%205004\/workplace\/Lab02\/src\/PayCheck.java"},{"path":"\/Lab02\/src","parentWorkspace":"\/Users\/eddie\/Desktop\/CS 5004\/workplace","name":"FibonacciCounter.java","lastModified":1664328907812,"locationURI":"file:\/Users\/eddie\/Desktop\/CS%205004\/workplace\/Lab02\/src\/FibonacciCounter.java"},{"path":"\/lab01\/test\/lab01","parentWorkspace":"\/Users\/eddie\/Desktop\/CS 5004\/workplace","name":"PersonTest.java","lastModified":1663249405105,"locationURI":"file:\/Users\/eddie\/Desktop\/CS%205004\/workplace\/lab01\/test\/lab01\/PersonTest.java"}]}